diff2d
