Metadata-Version: 1.0
Name: diff2d
Version: 0.1.8
Summary: Module for calculating 2D Diffusion.
Home-page: UNKNOWN
Author: Mirko Maelicke
Author-email: mirko.maelicke@kit.edu
License: CC BY-NC 4.0
Platform: UNKNOWN
